{"name":"LoginTest","testCaseName":"tests.GmailLoginTest","testSteps":[{"number":1,"description":"Open Gmail Page Step","duration":4132,"startTime":1447270289431,"screenshots":[{"screenshot":"c6d665ee819efed24d2311d74d6ddf3c_NONE.png"}],"result":"SUCCESS"},{"number":2,"description":"Login: \u003cspan class\u003d\u0027step-parameter\u0027\u003etestmail8601, qqqqqqqqqqq, testmail8601@gmail.com\u003c/span\u003e","duration":21724,"startTime":1447270293566,"screenshots":[{"screenshot":"e88b4fde67348b78a2da4ce1cbae843e_NONE.png"}],"exception":{"errorType":"java.lang.AssertionError","message":"User name from page  is different from model testmail8601@gmail.com","stackTrace":[{"declaringClass":"tests.GmailLoginTest","methodName":"LoginTest","fileName":"GmailLoginTest.java","lineNumber":46}]},"result":"FAILURE"}],"userStory":{"id":"requirements.Application.GmailLetterCheck.LetterCheck","storyName":"Letter check","storyClassName":"requirements.Application$GmailLetterCheck$LetterCheck","path":"requirements.Application.GmailLetterCheck","feature":{"id":"requirements.Application.GmailLetterCheck","name":"Gmail letter check"},"type":"story"},"title":"Login to Gmail","coreIssues":["CEMTA-35"],"tags":[{"name":"Letter check","type":"story"},{"name":"Gmail letter check","type":"feature"},{"name":"GmailTests","type":"feature"}],"startTime":1447270279012,"duration":36595,"testFailureCause":{"errorType":"java.lang.AssertionError","message":"User name from page  is different from model testmail8601@gmail.com","stackTrace":[{"declaringClass":"steps.LetterSteps","methodName":"login","fileName":"LetterSteps.java","lineNumber":26},{"declaringClass":"tests.GmailLoginTest","methodName":"LoginTest","fileName":"GmailLoginTest.java","lineNumber":46}]},"testFailureClassname":"java.lang.AssertionError","testFailureMessage":"User name from page  is different from model testmail8601@gmail.com","annotatedResult":"FAILURE","driver":"firefox","manual":false,"result":"FAILURE","issues":["CEMTA-35"]}